apicat/__init__.py
apicat/cli.py
apicat/config.py
apicat/core.py
apicat-0.0.7.dist-info/entry_points.txt
apicat-0.0.7.dist-info/METADATA
apicat-0.0.7.dist-info/WHEEL
apicat-0.0.7.dist-info/RECORD
