Metadata-Version: 2.1
Name: apicat
Version: 0.0.7
Summary: ApiCat 是一个API框架，它能帮助站长快速部署各种API。
Author: Yeying-Xingchen
Author-email: yeyingxingchen@yeah.net
Requires-Python: >=3.6
Classifier: Programming Language :: Python :: 3
Classifier: Programming Language :: Python :: 3.6
Classifier: Programming Language :: Python :: 3.7
Classifier: Programming Language :: Python :: 3.8
Classifier: Programming Language :: Python :: 3.9
Classifier: Programming Language :: Python :: 3.10
Classifier: Programming Language :: Python :: 3.11
Classifier: Programming Language :: Python :: 3.12
Requires-Dist: flask (>=2.3.2)
Requires-Dist: toml (>=0.10.2)
Requires-Dist: xhlog (>=0.0.1)
Requires-Dist: yaml (>=0.1.7)
